dendron/__init__.py
dendron/action_node.py
dendron/basic_types.py
dendron/behavior_tree.py
dendron/behavior_tree_factory.py
dendron/blackboard.py
dendron/condition_node.py
dendron/control_node.py
dendron/decorator_node.py
dendron/tree_node.py
dendron/xml_utilities.py
dendron/actions/__init__.py
dendron/actions/always_failure.py
dendron/actions/always_success.py
dendron/actions/async_action.py
dendron/actions/causal_lm_action.py
dendron/actions/generate_action.py
dendron/actions/image_lm_action.py
dendron/actions/loglikelihood_action.py
dendron/actions/loglikelihood_rolling_action.py
dendron/actions/pipeline_action.py
dendron/actions/simple_action.py
dendron/conditions/__init__.py
dendron/conditions/conjunction_node.py
dendron/conditions/disjunction_node.py
dendron/conditions/goal_node.py
dendron/conditions/lm_completion_condition.py
dendron/conditions/simple_condition.py
dendron/configs/__init__.py
dendron/configs/hflm_config.py
dendron/configs/lm_action_config.py
dendron/configs/lm_completion_config.py
dendron/controls/__init__.py
dendron/controls/fallback.py
dendron/controls/sequence.py
dendron/decorators/__init__.py
dendron/decorators/blackboard_history.py
dendron/decorators/force_failure.py
dendron/decorators/force_success.py
dendron/decorators/inverter.py
dendron/decorators/repeat.py
dendron/decorators/retry.py
dendron/decorators/run_once.py
dendron/decorators/timeout.py
dendron-0.2.0.dist-info/LICENSE
dendron-0.2.0.dist-info/METADATA
dendron-0.2.0.dist-info/WHEEL
dendron-0.2.0.dist-info/top_level.txt
dendron-0.2.0.dist-info/RECORD
