Metadata-Version: 2.2
Name: dendron
Version: 0.2.0
Summary: A library for working with LLMs and behavior trees.
Author: Richard Kelley
License: BSD License
Project-URL: Homepage, https://github.com/RichardKelley/dendron
Classifier: License :: OSI Approved :: BSD License
Classifier: Intended Audience :: Science/Research
Classifier: Topic :: Scientific/Engineering :: Artificial Intelligence
Requires-Python: >=3.7
License-File: LICENSE
Requires-Dist: torch>=2.0.0
Requires-Dist: transformers>=4.36.2
Requires-Dist: accelerate>=0.26.1
Requires-Dist: bitsandbytes>=0.42.0
Requires-Dist: sentencepiece>=0.1.99
Requires-Dist: protobuf>=4.25.2
Requires-Dist: hflm>=0.0.9
Provides-Extra: dev
Requires-Dist: pytest>=8.0.0; extra == "dev"
Dynamic: requires-python
